main_cli.py
commands/__init__.py
commands/chart.py
commands/deploy.py
commands/get_scan_data.py
commands/scan.py
commands/search.py
commands/transfer.py
commands/upload.py
portal_cli-0.1.20.dist-info/licenses/LICENSE
portal_cli-0.1.20.dist-info/METADATA
portal_cli-0.1.20.dist-info/WHEEL
portal_cli-0.1.20.dist-info/entry_points.txt
portal_cli-0.1.20.dist-info/top_level.txt
portal_cli-0.1.20.dist-info/RECORD
