Metadata-Version: 2.4
Name: portal-cli
Version: 0.1.20
Summary: A CLI for portal image management.
Home-page: https://github.com/k8or-orbit-aws/portal-cli
Author: AI Cloud Services LLC
Author-email: barb.rock@k8or.com
Classifier: Programming Language :: Python :: 3
Classifier: License :: OSI Approved :: MIT License
Classifier: Operating System :: OS Independent
Requires-Python: >=3.6
License-File: LICENSE
Requires-Dist: click
Requires-Dist: requests
Dynamic: author
Dynamic: author-email
Dynamic: classifier
Dynamic: description
Dynamic: description-content-type
Dynamic: home-page
Dynamic: license-file
Dynamic: requires-dist
Dynamic: requires-python
Dynamic: summary
